pyOSOAA/__init__.py
pyOSOAA/constants.py
pyOSOAA/osoaa.py
pyOSOAA/osoaahelpers.py
pyOSOAA/outputs.py
pyOSOAA-1.5.dist-info/LICENSE
pyOSOAA-1.5.dist-info/METADATA
pyOSOAA-1.5.dist-info/WHEEL
pyOSOAA-1.5.dist-info/top_level.txt
pyOSOAA-1.5.dist-info/RECORD
