Metadata-Version: 2.1
Name: pyOSOAA
Version: 1.5
Summary: pyOSOAA is a python interface for the Ocean Successive Orders with Atmosphere - Advanced (OSOAA) radiative transfer.
Home-page: https://github.com/fnemina/pyOSOAA
Author: Francisco Nemiña
Author-email: Francisco Nemiña <fnemina@conae.gov.ar>
License: GPL-3.0
Project-URL: Homepage, https://github.com/fnemina/pyOSOAA
Project-URL: Bug Tracker, https://github.com/fnemina/pyOSOAA/issues
Classifier: Development Status :: 3 - Alpha
Classifier: Intended Audience :: Science/Research
Classifier: Topic :: Scientific/Engineering :: Atmospheric Science
Classifier: Topic :: Scientific/Engineering :: Physics
Classifier: Topic :: Software Development :: Libraries :: Python Modules
Classifier: Programming Language :: Python :: 3
Classifier: License :: OSI Approved :: GNU General Public License v3 (GPLv3)
Classifier: Operating System :: OS Independent
Requires-Python: >=3.7
License-File: LICENSE
Requires-Dist: numpy
Requires-Dist: matplotlib
Requires-Dist: scipy
